{

	"new pavilion.new pavillion:varn": {
		"specialty": {
			"creature": null,
			"bonuses": {
                "attack": {
					"subtype": "primarySkill.attack",
					"type": "PRIMARY_SKILL",
					"val": 0,
                    "targetSourceType" : "CREATURE_ABILITY",
                    "valueType": "PERCENT_TO_TARGET_TYPE",
                    "updater": {
                        "parameters": [57],
                        "type": "GROWS_WITH_LEVEL"
					},
					"limiters": [
						{
							"parameters": ["anubis", true],
							"type": "CREATURE_TYPE_LIMITER"
						}
					],
				},
                "defence": {
					"subtype": "primarySkill.defence",
					"type": "PRIMARY_SKILL",
					"val": 0,
                    "targetSourceType" : "CREATURE_ABILITY",
                    "valueType": "PERCENT_TO_TARGET_TYPE",
                    "updater": {
                        "parameters": [57],
                        "type": "GROWS_WITH_LEVEL"
					},
					"limiters": [
						{
							"parameters": ["anubis", true],
							"type": "CREATURE_TYPE_LIMITER"
						}
					],
				},
				"speed": {
					"type": "STACKS_SPEED",
					"val": 1,
					"limiters": [
						{
							"parameters": ["anubis", true],
							"type": "CREATURE_TYPE_LIMITER"
						}
					]
				}
            }
		},

        "texts": {
            "specialty": {
                "name": "冥神使",
                "description": "每7级提高冥神使及其升级形态20%的攻击力和防御力。速度+1。"
            }
        }
	},

	"new pavilion.new pavillion:amesh": {
		"specialty": {
			"creature": null,
			"bonuses": {
                "attack": {
					"subtype": "primarySkill.attack",
					"type": "PRIMARY_SKILL",
					"val": 0,
                    "targetSourceType" : "CREATURE_ABILITY",
                    "valueType": "PERCENT_TO_TARGET_TYPE",
                    "updater": {
                        "parameters": [70],
                        "type": "GROWS_WITH_LEVEL"
					},
					"limiters": [
						{
							"parameters": ["sphinx", true],
							"type": "CREATURE_TYPE_LIMITER"
						}
					],
				},
                "defence": {
					"subtype": "primarySkill.defence",
					"type": "PRIMARY_SKILL",
					"val": 0,
                    "targetSourceType" : "CREATURE_ABILITY",
                    "valueType": "PERCENT_TO_TARGET_TYPE",
                    "updater": {
                        "parameters": [70],
                        "type": "GROWS_WITH_LEVEL"
					},
					"limiters": [
						{
							"parameters": ["sphinx", true],
							"type": "CREATURE_TYPE_LIMITER"
						}
					],
				},
				"speed": {
					"type": "STACKS_SPEED",
					"val": 1,
					"limiters": [
						{
							"parameters": ["sphinx", true],
							"type": "CREATURE_TYPE_LIMITER"
						}
					]
				}
            }
		},

        "texts": {
            "specialty": {
                "name": "人面狮",
                "description": "每6级提高人面狮及其升级形态20%的攻击力和防御力。速度+1。"
            }
        }
	},

	"new pavilion.new pavillion:cassandra": {
		"specialty": {
			"creature": null,
			"bonuses": {
                "attack": {
					"subtype": "primarySkill.attack",
					"type": "PRIMARY_SKILL",
					"val": 0,
                    "targetSourceType" : "CREATURE_ABILITY",
                    "valueType": "PERCENT_TO_TARGET_TYPE",
                    "updater": {
                        "parameters": [80],
                        "type": "GROWS_WITH_LEVEL"
					},
					"limiters": [
						{
							"parameters": ["ammut", true],
							"type": "CREATURE_TYPE_LIMITER"
						}
					],
				},
                "defence": {
					"subtype": "primarySkill.defence",
					"type": "PRIMARY_SKILL",
					"val": 0,
                    "targetSourceType" : "CREATURE_ABILITY",
                    "valueType": "PERCENT_TO_TARGET_TYPE",
                    "updater": {
                        "parameters": [80],
                        "type": "GROWS_WITH_LEVEL"
					},
					"limiters": [
						{
							"parameters": ["ammut", true],
							"type": "CREATURE_TYPE_LIMITER"
						}
					],
				},
				"speed": {
					"type": "STACKS_SPEED",
					"val": 1,
					"limiters": [
						{
							"parameters": ["ammut", true],
							"type": "CREATURE_TYPE_LIMITER"
						}
					]
				}
            }
		},

        "texts": {
            "specialty": {
                "name": "恐鳄",
                "description": "每5级提高恐鳄及其升级形态20%的攻击力和防御力。速度+1。"
            }
        }
	},

	"new pavilion.new pavillion:menet": {
		"specialty": {
			"creature": null,
			"bonuses": {
                "attack": {
					"subtype": "primarySkill.attack",
					"type": "PRIMARY_SKILL",
					"val": 0,
                    "targetSourceType" : "CREATURE_ABILITY",
                    "valueType": "PERCENT_TO_TARGET_TYPE",
                    "updater": {
                        "parameters": [100],
                        "type": "GROWS_WITH_LEVEL"
					},
					"limiters": [
						{
							"parameters": ["sekhmet", true],
							"type": "CREATURE_TYPE_LIMITER"
						}
					],
				},
                "defence": {
					"subtype": "primarySkill.defence",
					"type": "PRIMARY_SKILL",
					"val": 0,
                    "targetSourceType" : "CREATURE_ABILITY",
                    "valueType": "PERCENT_TO_TARGET_TYPE",
                    "updater": {
                        "parameters": [100],
                        "type": "GROWS_WITH_LEVEL"
					},
					"limiters": [
						{
							"parameters": ["sekhmet", true],
							"type": "CREATURE_TYPE_LIMITER"
						}
					],
				},
				"speed": {
					"type": "STACKS_SPEED",
					"val": 1,
					"limiters": [
						{
							"parameters": ["sekhmet", true],
							"type": "CREATURE_TYPE_LIMITER"
						}
					]
				}
            }
		},

        "texts": {
            "specialty": {
                "name": "谜影侍女",
                "description": "每4级提高谜影侍女及其升级形态20%的攻击力和防御力。速度+1。"
            }
        }
	},

	"new pavilion.new pavillion:ibrahim": {
		"specialty": {
			"creature": null,
			"bonuses": {
                "attack": {
					"subtype": "primarySkill.attack",
					"type": "PRIMARY_SKILL",
					"val": 0,
                    "targetSourceType" : "CREATURE_ABILITY",
                    "valueType": "PERCENT_TO_TARGET_TYPE",
                    "updater": {
                        "parameters": [133],
                        "type": "GROWS_WITH_LEVEL"
					},
					"limiters": [
						{
							"parameters": ["camelRider", true],
							"type": "CREATURE_TYPE_LIMITER"
						}
					],
				},
                "defence": {
					"subtype": "primarySkill.defence",
					"type": "PRIMARY_SKILL",
					"val": 0,
                    "targetSourceType" : "CREATURE_ABILITY",
                    "valueType": "PERCENT_TO_TARGET_TYPE",
                    "updater": {
                        "parameters": [133],
                        "type": "GROWS_WITH_LEVEL"
					},
					"limiters": [
						{
							"parameters": ["camelRider", true],
							"type": "CREATURE_TYPE_LIMITER"
						}
					],
				},
				"speed": {
					"type": "STACKS_SPEED",
					"val": 1,
					"limiters": [
						{
							"parameters": ["camelRider", true],
							"type": "CREATURE_TYPE_LIMITER"
						}
					]
				}
            }
		},

        "texts": {
            "specialty": {
                "name": "骆驼骑兵",
                "description": "每3级提高骆驼骑兵及其升级形态20%的攻击力和防御力。速度+1。"
            }
        }
	},

	"new pavilion.new pavillion:azarias": {
		"specialty": {
			"creature": null,
			"bonuses": {
                "attack": {
					"subtype": "primarySkill.attack",
					"type": "PRIMARY_SKILL",
					"val": 0,
                    "targetSourceType" : "CREATURE_ABILITY",
                    "valueType": "PERCENT_TO_TARGET_TYPE",
                    "updater": {
                        "parameters": [200],
                        "type": "GROWS_WITH_LEVEL"
					},
					"limiters": [
						{
							"parameters": ["wadjet", true],
							"type": "CREATURE_TYPE_LIMITER"
						}
					],
				},
                "defence": {
					"subtype": "primarySkill.defence",
					"type": "PRIMARY_SKILL",
					"val": 0,
                    "targetSourceType" : "CREATURE_ABILITY",
                    "valueType": "PERCENT_TO_TARGET_TYPE",
                    "updater": {
                        "parameters": [200],
                        "type": "GROWS_WITH_LEVEL"
					},
					"limiters": [
						{
							"parameters": ["wadjet", true],
							"type": "CREATURE_TYPE_LIMITER"
						}
					],
				},
				"speed": {
					"type": "STACKS_SPEED",
					"val": 1,
					"limiters": [
						{
							"parameters": ["wadjet", true],
							"type": "CREATURE_TYPE_LIMITER"
						}
					]
				}
            }
		},

        "texts": {
            "specialty": {
                "name": "沙蛇",
                "description": "每2级提高沙蛇及其升级形态20%的攻击力和防御力。速度+1。"
            }
        }
	},

	"new pavilion.new pavillion:marzum": {
		"specialty": {
			"creature": null,
			"bonuses": {
                "attack": {
					"subtype": "primarySkill.attack",
					"type": "PRIMARY_SKILL",
					"val": 0,
                    "targetSourceType" : "CREATURE_ABILITY",
                    "valueType": "PERCENT_TO_TARGET_TYPE",
                    "updater": {
                        "parameters": [200],
                        "type": "GROWS_WITH_LEVEL"
					},
					"limiters": [
						{
							"parameters": ["whipper", true],
							"type": "CREATURE_TYPE_LIMITER"
						}
					],
				},
                "defence": {
					"subtype": "primarySkill.defence",
					"type": "PRIMARY_SKILL",
					"val": 0,
                    "targetSourceType" : "CREATURE_ABILITY",
                    "valueType": "PERCENT_TO_TARGET_TYPE",
                    "updater": {
                        "parameters": [200],
                        "type": "GROWS_WITH_LEVEL"
					},
					"limiters": [
						{
							"parameters": ["whipper", true],
							"type": "CREATURE_TYPE_LIMITER"
						}
					],
				},
				"speed": {
					"type": "STACKS_SPEED",
					"val": 1,
					"limiters": [
						{
							"parameters": ["whipper", true],
							"type": "CREATURE_TYPE_LIMITER"
						}
					]
				}
            }
		},

        "texts": {
            "specialty": {
                "name": "督工",
                "description": "每1级提高督工及其升级形态10%的攻击力和防御力。速度+1。"
            }
        }
	}
}
