{
	"cassandra" :
	{
		"class" : "vizier",
		"female" : true,

		"texts" :
		{
			"name" : "卡桑德拉",
			"biography" : "每次以高级法官的身份来解决行省内的问题时，卡桑德拉冷酷而不屈的性格就会显现出来。她的不朽精神和严苛的奖惩使她获得了阿穆特的同情，尤其是每次执行都会给它们带来丰盛的节日。",
			"specialty" :
			{
				"description" : "达到5级以后提高恐鳄或太阳鳄的攻击力与防御力。",
				"tooltip" : "Creature Bonus: Ammuts",
				"name" : "恐鳄"
			}
		},
		
		"images" :
		{
			"specialtySmall" : "speciconsPavilion/un32Ammu.bmp",
			"specialtyLarge" : "speciconsPavilion/un44Ammu.bmp",
			"large" : "heroportraitsPavilion/Cassandra.png",
			"small" : "heroportraitsPavilion/CassandraSmall.png"
		},

		"army" :
		[
			{
				"creature" : "whipper",
				"max" : 25,
				"min" : 15
			},
			{
				"creature" : "wadjet",
				"max" : 8,
				"min" : 4
			},
			{
				"creature" : "camelRider",
				"max" : 4,
				"min" : 2
			}
		],

		"skills" :
		[
			{
				"level" : "basic",
				"skill" : "learning"
			},
			{
				"level" : "basic",
				"skill" : "diplomacy"
			}
		],
		
		"specialty" : {
			"creature" : "ammut"
		}
	}
}
